yard/__init__.py
yard/curve.py
yard/data.py
yard/mathematics.py
yard/scripts/__init__.py
yard/scripts/auc.py
yard/scripts/plot.py
yard/scripts/significance.py
yard/significance.py
yard/transform.py
yard/utils.py
yard/version.py
yard-0.3.0.dist-info/entry_points.txt
yard-0.3.0.dist-info/LICENSE
yard-0.3.0.dist-info/WHEEL
yard-0.3.0.dist-info/METADATA
yard-0.3.0.dist-info/RECORD
