Metadata-Version: 2.1
Name: yard
Version: 0.3.0
Summary: Yet another ROC curve drawer
Home-page: https://github.com/ntamas/yard
License: MIT
Keywords: roc curve,statistics,mathematics,machine learning,auc
Author: Tamas Nepusz
Author-email: ntamas@gmail.com
Requires-Python: >=3.7,<4.0
Classifier: Development Status :: 4 - Beta
Classifier: Environment :: Console
Classifier: Intended Audience :: Developers
Classifier: Intended Audience :: Science/Research
Classifier: License :: OSI Approved :: MIT License
Classifier: Operating System :: OS Independent
Classifier: Programming Language :: Python
Classifier: Programming Language :: Python :: 3
Classifier: Programming Language :: Python :: 3.7
Classifier: Programming Language :: Python :: 3.8
Classifier: Programming Language :: Python :: 3.9
Classifier: Topic :: Scientific/Engineering :: Artificial Intelligence
Classifier: Topic :: Scientific/Engineering :: Bio-Informatics
Classifier: Topic :: Scientific/Engineering :: Mathematics
Classifier: Topic :: Utilities
Provides-Extra: plotting
Requires-Dist: matplotlib (>=3.4.1,<4.0.0); extra == "plotting"
Project-URL: Repository, https://github.com/ntamas/yard
